Metadata-Version: 1.1
Name: awsPySqsListener
Version: 0.1.0
Summary: A simple Python SQS utility package
Home-page: https://github.com/balan2010/python-sqs-listener
Author: Umabalan Nagarajan
Author-email: umabalan2010@gmail.com
License: Apache Software License
Keywords: aws sqs listener and launcher
Platform: UNKNOWN
Classifier: Development Status :: 3 - Alpha
Classifier: Intended Audience :: Developers
Classifier: Topic :: Software Development :: Libraries
Classifier: License :: OSI Approved :: Apache Software License
Classifier: Programming Language :: Python :: 2.7
Classifier: Programming Language :: Python :: 3.5
